serveM/VERSION
serveM/__init__.py
serveM/main.py
serveM/settings.py
serveM/public/index.html
serveM/screencast/__init__.py
serveM/screencast/portal.py
serveM/screencast/stream_man.py
serveM/server/__init__.py
serveM/server/server.py
serveM/server/static_routes.py
serveM/server/stream_route.py
serveM-0.1.0.dist-info/LICENSE
serveM-0.1.0.dist-info/METADATA
serveM-0.1.0.dist-info/WHEEL
serveM-0.1.0.dist-info/entry_points.txt
serveM-0.1.0.dist-info/top_level.txt
serveM-0.1.0.dist-info/RECORD
