Metadata-Version: 2.1
Name: serveM
Version: 0.1.0
Summary: A simple screen sharing server for modern GNU/LINUX desktops!
Author-email: "@bRuttaZz" <agrajpdasprivate@gmail.com>
License: GNU GENERAL PUBLIC LICENSE
Project-URL: Repository, https://github.com/bRuttaZz/serveM.git
Keywords: stmp,sitty-talky,sittytalky,LAN,WLAN,peer-discovery,Messaging,protocol,multicast dns,dns,udp,tcp
Classifier: Development Status :: 4 - Beta
Classifier: Intended Audience :: End Users/Desktop 
Classifier: Intended Audience :: Developers
Classifier: License :: OSI Approved :: GNU General Public License v3 (GPLv3)
Classifier: Operating System :: POSIX
Classifier: Operating System :: POSIX :: Linux
Classifier: Operating System :: Unix
Classifier: Programming Language :: Python :: 3.8
Classifier: Programming Language :: Python :: 3.9
Classifier: Programming Language :: Python :: 3.10
Classifier: Programming Language :: Python :: 3.11
Classifier: Programming Language :: Python :: 3.12
Classifier: Programming Language :: Python :: 3.13
Classifier: Topic :: Adaptive Technologies
Classifier: Topic :: Internet
Classifier: Topic :: Communications :: File Sharing
Classifier: Topic :: Desktop Environment :: Window Managers
Classifier: Natural Language :: English
Requires-Python: >=3.8
License-File: LICENSE
Requires-Dist: uvicorn >=0.30.1
